tree_sitter_kconfig-1.3.0.dist-info/top_level.txt
tree_sitter_kconfig-1.3.0.dist-info/RECORD
tree_sitter_kconfig-1.3.0.dist-info/LICENSE
tree_sitter_kconfig-1.3.0.dist-info/METADATA
tree_sitter_kconfig-1.3.0.dist-info/WHEEL
tree_sitter_kconfig/__init__.py
tree_sitter_kconfig/_binding.abi3.so
tree_sitter_kconfig/binding.c
tree_sitter_kconfig/__init__.pyi
tree_sitter_kconfig/py.typed
tree_sitter_kconfig/queries/folds.scm
tree_sitter_kconfig/queries/highlights.scm
tree_sitter_kconfig/queries/indents.scm
tree_sitter_kconfig/queries/injections.scm
tree_sitter_kconfig/queries/locals.scm
